[{"name":"clound_run_utils","qualifiedName":"clound_run_utils","href":"util_clound_run_utils/util_clound_run_utils-library.html","type":"library","overriddenDepth":0,"packageName":"dart_shelf_firebase_example"},{"name":"currentProjectId","qualifiedName":"clound_run_utils.currentProjectId","href":"util_clound_run_utils/currentProjectId.html","type":"function","overriddenDepth":0,"packageName":"dart_shelf_firebase_example","enclosedBy":{"name":"clound_run_utils","type":"library"}},{"name":"gcpProjectIdEnvironmentVariables","qualifiedName":"clound_run_utils.gcpProjectIdEnvironmentVariables","href":"util_clound_run_utils/gcpProjectIdEnvironmentVariables-constant.html","type":"top-level constant","overriddenDepth":0,"packageName":"dart_shelf_firebase_example","enclosedBy":{"name":"clound_run_utils","type":"library"}},{"name":"listenPort","qualifiedName":"clound_run_utils.listenPort","href":"util_clound_run_utils/listenPort.html","type":"function","overriddenDepth":0,"packageName":"dart_shelf_firebase_example","enclosedBy":{"name":"clound_run_utils","type":"library"}},{"name":"serveHandler","qualifiedName":"clound_run_utils.serveHandler","href":"util_clound_run_utils/serveHandler.html","type":"function","overriddenDepth":0,"packageName":"dart_shelf_firebase_example","enclosedBy":{"name":"clound_run_utils","type":"library"}},{"name":"terminateRequestFuture","qualifiedName":"clound_run_utils.terminateRequestFuture","href":"util_clound_run_utils/terminateRequestFuture.html","type":"function","overriddenDepth":0,"packageName":"dart_shelf_firebase_example","enclosedBy":{"name":"clound_run_utils","type":"library"}},{"name":"config","qualifiedName":"config","href":"config_config/config_config-library.html","type":"library","overriddenDepth":0,"packageName":"dart_shelf_firebase_example"},{"name":"projectId","qualifiedName":"config.projectId","href":"config_config/projectId-constant.html","type":"top-level constant","overriddenDepth":0,"packageName":"dart_shelf_firebase_example","enclosedBy":{"name":"config","type":"library"}},{"name":"dart_shelf_firebase_example","qualifiedName":"dart_shelf_firebase_example","href":"dart_shelf_firebase_example/dart_shelf_firebase_example-library.html","type":"library","overriddenDepth":0,"packageName":"dart_shelf_firebase_example"},{"name":"AppModule","qualifiedName":"dart_shelf_firebase_example.AppModule","href":"dart_shelf_firebase_example/AppModule-class.html","type":"class","overriddenDepth":0,"packageName":"dart_shelf_firebase_example","enclosedBy":{"name":"dart_shelf_firebase_example","type":"library"}},{"name":"AppModule","qualifiedName":"dart_shelf_firebase_example.AppModule.AppModule","href":"dart_shelf_firebase_example/AppModule/AppModule.html","type":"constructor","overriddenDepth":0,"packageName":"dart_shelf_firebase_example","enclosedBy":{"name":"AppModule","type":"class"}},{"name":"appController","qualifiedName":"dart_shelf_firebase_example.AppModule.appController","href":"dart_shelf_firebase_example/AppModule/appController.html","type":"property","overriddenDepth":0,"packageName":"dart_shelf_firebase_example","enclosedBy":{"name":"AppModule","type":"class"}},{"name":"appMiddleware","qualifiedName":"dart_shelf_firebase_example.AppModule.appMiddleware","href":"dart_shelf_firebase_example/AppModule/appMiddleware.html","type":"property","overriddenDepth":0,"packageName":"dart_shelf_firebase_example","enclosedBy":{"name":"AppModule","type":"class"}},{"name":"authClient","qualifiedName":"dart_shelf_firebase_example.AppModule.authClient","href":"dart_shelf_firebase_example/AppModule/authClient.html","type":"property","overriddenDepth":0,"packageName":"dart_shelf_firebase_example","enclosedBy":{"name":"AppModule","type":"class"}},{"name":"router","qualifiedName":"dart_shelf_firebase_example.AppModule.router","href":"dart_shelf_firebase_example/AppModule/router.html","type":"property","overriddenDepth":0,"packageName":"dart_shelf_firebase_example","enclosedBy":{"name":"AppModule","type":"class"}},{"name":"userModule","qualifiedName":"dart_shelf_firebase_example.AppModule.userModule","href":"dart_shelf_firebase_example/AppModule/userModule.html","type":"property","overriddenDepth":0,"packageName":"dart_shelf_firebase_example","enclosedBy":{"name":"AppModule","type":"class"}},{"name":"UserModule","qualifiedName":"dart_shelf_firebase_example.UserModule","href":"dart_shelf_firebase_example/UserModule-class.html","type":"class","overriddenDepth":0,"packageName":"dart_shelf_firebase_example","enclosedBy":{"name":"dart_shelf_firebase_example","type":"library"}},{"name":"UserModule","qualifiedName":"dart_shelf_firebase_example.UserModule.UserModule","href":"dart_shelf_firebase_example/UserModule/UserModule.html","type":"constructor","overriddenDepth":0,"packageName":"dart_shelf_firebase_example","enclosedBy":{"name":"UserModule","type":"class"}},{"name":"authClient","qualifiedName":"dart_shelf_firebase_example.UserModule.authClient","href":"dart_shelf_firebase_example/UserModule/authClient.html","type":"property","overriddenDepth":0,"packageName":"dart_shelf_firebase_example","enclosedBy":{"name":"UserModule","type":"class"}},{"name":"router","qualifiedName":"dart_shelf_firebase_example.UserModule.router","href":"dart_shelf_firebase_example/UserModule/router.html","type":"property","overriddenDepth":0,"packageName":"dart_shelf_firebase_example","enclosedBy":{"name":"UserModule","type":"class"}},{"name":"userController","qualifiedName":"dart_shelf_firebase_example.UserModule.userController","href":"dart_shelf_firebase_example/UserModule/userController.html","type":"property","overriddenDepth":0,"packageName":"dart_shelf_firebase_example","enclosedBy":{"name":"UserModule","type":"class"}},{"name":"userMiddleware","qualifiedName":"dart_shelf_firebase_example.UserModule.userMiddleware","href":"dart_shelf_firebase_example/UserModule/userMiddleware.html","type":"property","overriddenDepth":0,"packageName":"dart_shelf_firebase_example","enclosedBy":{"name":"UserModule","type":"class"}},{"name":"get_auth_client","qualifiedName":"get_auth_client","href":"util_get_auth_client/util_get_auth_client-library.html","type":"library","overriddenDepth":0,"packageName":"dart_shelf_firebase_example"},{"name":"getAuthClient","qualifiedName":"get_auth_client.getAuthClient","href":"util_get_auth_client/getAuthClient.html","type":"function","overriddenDepth":0,"packageName":"dart_shelf_firebase_example","enclosedBy":{"name":"get_auth_client","type":"library"}}]
